{
   "directed":false,
   "graph":{
      
   },
   "links":[
      {
         "source":"Football",
         "target":"Northern England"
      },
      {
         "source":"Football",
         "target":"North American"
      },
      {
         "source":"Football",
         "target":"The Football League"
      },
      {
         "source":"Football",
         "target":"Richard Thomas"
      },
      {
         "source":"Football",
         "target":"United Hospitals Challenge Cup"
      },
      {
         "source":"Northern England",
         "target":"Northwest England"
      },
      {
         "source":"Northern England",
         "target":"United Kingdom"
      },
      {
         "source":"Northern England",
         "target":"Greater London"
      },
      {
         "source":"Northern England",
         "target":"Great Britain"
      },
      {
         "source":"Northern England",
         "target":"South Wales"
      },
      {
         "source":"North American",
         "target":"North America"
      },
      {
         "source":"North American",
         "target":"American Civil War"
      },
      {
         "source":"North American",
         "target":"Native Americans"
      },
      {
         "source":"North American",
         "target":"New York City"
      },
      {
         "source":"North American",
         "target":"George Washington"
      },
      {
         "source":"The Football League",
         "target":"English Football League"
      },
      {
         "source":"The Football League",
         "target":"Premier League"
      },
      {
         "source":"The Football League",
         "target":"Football League Second Division"
      },
      {
         "source":"The Football League",
         "target":"Football League First Division"
      },
      {
         "source":"The Football League",
         "target":"Football League Third Division"
      },
      {
         "source":"Richard Thomas",
         "target":"Richard Earl Thomas"
      },
      {
         "source":"Richard Thomas",
         "target":"The Waltons"
      },
      {
         "source":"Richard Thomas",
         "target":"The Americans"
      },
      {
         "source":"Richard Thomas",
         "target":"Columbia University"
      },
      {
         "source":"Richard Thomas",
         "target":"American"
      },
      {
         "source":"United Hospitals Challenge Cup",
         "target":"United Hospitals RFC"
      },
      {
         "source":"United Hospitals Challenge Cup",
         "target":"London"
      },
      {
         "source":"United Hospitals Challenge Cup",
         "target":"St Georges Hospital"
      },
      {
         "source":"United Hospitals Challenge Cup",
         "target":"Guys Hospital"
      },
      {
         "source":"United Hospitals Challenge Cup",
         "target":"Calcutta Cup"
      }
   ],
   "multigraph":false,
   "nodes":[
      {
         "id":"Football"
      },
      {
         "id":"Northern England"
      },
      {
         "id":"North American"
      },
      {
         "id":"The Football League"
      },
      {
         "id":"Richard Thomas"
      },
      {
         "id":"United Hospitals Challenge Cup"
      },
      {
         "id":"Northwest England"
      },
      {
         "id":"United Kingdom"
      },
      {
         "id":"Greater London"
      },
      {
         "id":"Great Britain"
      },
      {
         "id":"South Wales"
      },
      {
         "id":"North America"
      },
      {
         "id":"American Civil War"
      },
      {
         "id":"Native Americans"
      },
      {
         "id":"New York City"
      },
      {
         "id":"George Washington"
      },
      {
         "id":"English Football League"
      },
      {
         "id":"Premier League"
      },
      {
         "id":"Football League Second Division"
      },
      {
         "id":"Football League First Division"
      },
      {
         "id":"Football League Third Division"
      },
      {
         "id":"Richard Earl Thomas"
      },
      {
         "id":"The Waltons"
      },
      {
         "id":"The Americans"
      },
      {
         "id":"Columbia University"
      },
      {
         "id":"American"
      },
      {
         "id":"United Hospitals RFC"
      },
      {
         "id":"London"
      },
      {
         "id":"St Georges Hospital"
      },
      {
         "id":"Guys Hospital"
      },
      {
         "id":"Calcutta Cup"
      }
   ]
}